PDAnalysis/__init__.py
PDAnalysis/deformation.py
PDAnalysis/pdb_parser.py
PDAnalysis/protein.py
PDAnalysis/utils.py
PDAnalysis-0.0.4.dist-info/LICENSE.txt
PDAnalysis-0.0.4.dist-info/METADATA
PDAnalysis-0.0.4.dist-info/WHEEL
PDAnalysis-0.0.4.dist-info/entry_points.txt
PDAnalysis-0.0.4.dist-info/top_level.txt
PDAnalysis-0.0.4.dist-info/RECORD
