Metadata-Version: 2.1
Name: PDAnalysis
Version: 0.0.4
Summary: Software for analysing deformation between protein structures.
Home-page: https://github.com/mirabdi/PDAnalysis
Author: John M. McBride
Author-email: jmmcbride@protonmail.com
License: UNKNOWN
Keywords: science biology biophysics molecular structural
Platform: UNKNOWN
Classifier: Development Status :: 3 - Alpha
Classifier: Intended Audience :: Science/Research
Classifier: License :: OSI Approved :: MIT License
Classifier: Programming Language :: Python :: 3
Classifier: Programming Language :: Python :: 3.7
Classifier: Programming Language :: Python :: 3.8
Classifier: Programming Language :: Python :: 3.9
Classifier: Programming Language :: Python :: 3.10
Classifier: Programming Language :: Python :: 3.11
Classifier: Programming Language :: C
Classifier: Topic :: Scientific/Engineering
Classifier: Topic :: Scientific/Engineering :: Bio-Informatics
Classifier: Topic :: Scientific/Engineering :: Chemistry
Classifier: Topic :: Software Development :: Libraries :: Python Modules
Provides: PDAnalysis
Requires-Python: >=3.7
License-File: LICENSE.txt
Requires-Dist: numpy (>=1.22.3)
Requires-Dist: biopython (>=1.80)
Requires-Dist: pandas (>=1.4.4)
Requires-Dist: scipy (>=1.5.0)
